<?xml version="1.0" encoding="UTF-8"?>
<objects serializationModel="Studio.02.00.00">
	<object class="AudioFile" id="{73634385-0e55-44ab-baf7-2618db890652}">
		<property name="assetPath">
			<value>sx_wgh_game_int_weapon_shotgun_loadshell_ 01.wav</value>
		</property>
		<property name="frequencyInKHz">
			<value>48</value>
		</property>
		<property name="channelCount">
			<value>1</value>
		</property>
		<property name="length">
			<value>0.57495833333333335</value>
		</property>
		<relationship name="masterAssetFolder">
			<destination>{6e3e2055-3c6c-4108-a84c-1a76373f8264}</destination>
		</relationship>
	</object>
</objects>
